[
  {
    "movie_id": "6MXNMUqLfH29PBjfmBYswh",
    "movie_name": "Guru Aama",
    "total_shows": 8,
    "seats": 1715,
    "sold": 9,
    "reserved": 11,
    "available": 1695,
    "housefull": 0,
    "fastfilling": 0,
    "venues": [
      {
        "venue": "fcube",
        "total_shows": 1,
        "seats": 198,
        "sold": 4,
        "reserved": 10,
        "available": 184,
        "housefull": 0,
        "fastfilling": 0
      },
      {
        "venue": "qfx-bhaktapur",
        "total_shows": 1,
        "seats": 247,
        "sold": 2,
        "reserved": 0,
        "available": 245,
        "housefull": 0,
        "fastfilling": 0
      },
      {
        "venue": "ranjana-cineplex",
        "total_shows": 1,
        "seats": 164,
        "sold": 3,
        "reserved": 0,
        "available": 161,
        "housefull": 0,
        "fastfilling": 0
      },
      {
        "venue": "bishwojyoti-cineplex",
        "total_shows": 1,
        "seats": 201,
        "sold": 0,
        "reserved": 1,
        "available": 200,
        "housefull": 0,
        "fastfilling": 0
      },
      {
        "venue": "ini-qbox-butwal",
        "total_shows": 1,
        "seats": 196,
        "sold": 0,
        "reserved": 0,
        "available": 196,
        "housefull": 0,
        "fastfilling": 0
      },
      {
        "venue": "ini-cinemas-nb-center",
        "total_shows": 1,
        "seats": 177,
        "sold": 0,
        "reserved": 0,
        "available": 177,
        "housefull": 0,
        "fastfilling": 0
      },
      {
        "venue": "ini-cinemas-devchuli",
        "total_shows": 1,
        "seats": 292,
        "sold": 0,
        "reserved": 0,
        "available": 292,
        "housefull": 0,
        "fastfilling": 0
      },
      {
        "venue": "ini-lotse-ktm",
        "total_shows": 1,
        "seats": 240,
        "sold": 0,
        "reserved": 0,
        "available": 240,
        "housefull": 0,
        "fastfilling": 0
      }
    ]
  },
  {
    "movie_id": "r38CGCEZJgCW4CaDSnxH9A",
    "movie_name": "Lalibazar",
    "total_shows": 34,
    "seats": 7305,
    "sold": 25,
    "reserved": 138,
    "available": 7142,
    "housefull": 0,
    "fastfilling": 0,
    "venues": [
      {
        "venue": "fcube",
        "total_shows": 3,
        "seats": 632,
        "sold": 21,
        "reserved": 75,
        "available": 536,
        "housefull": 0,
        "fastfilling": 0
      },
      {
        "venue": "qfx-bhaktapur",
        "total_shows": 4,
        "seats": 990,
        "sold": 4,
        "reserved": 61,
        "available": 925,
        "housefull": 0,
        "fastfilling": 0
      },
      {
        "venue": "ranjana-cineplex",
        "total_shows": 4,
        "seats": 1004,
        "sold": 0,
        "reserved": 0,
        "available": 1004,
        "housefull": 0,
        "fastfilling": 0
      },
      {
        "venue": "birat-cine",
        "total_shows": 2,
        "seats": 244,
        "sold": 0,
        "reserved": 0,
        "available": 244,
        "housefull": 0,
        "fastfilling": 0
      },
      {
        "venue": "qfx-cineflix-itahari",
        "total_shows": 2,
        "seats": 268,
        "sold": 0,
        "reserved": 0,
        "available": 268,
        "housefull": 0,
        "fastfilling": 0
      },
      {
        "venue": "ini-lotse-ktm",
        "total_shows": 4,
        "seats": 960,
        "sold": 0,
        "reserved": 0,
        "available": 960,
        "housefull": 0,
        "fastfilling": 0
      },
      {
        "venue": "ini-cinemas-nb-center",
        "total_shows": 4,
        "seats": 840,
        "sold": 0,
        "reserved": 0,
        "available": 840,
        "housefull": 0,
        "fastfilling": 0
      },
      {
        "venue": "bishwojyoti-cineplex",
        "total_shows": 2,
        "seats": 402,
        "sold": 0,
        "reserved": 2,
        "available": 400,
        "housefull": 0,
        "fastfilling": 0
      },
      {
        "venue": "ini-qbox-butwal",
        "total_shows": 4,
        "seats": 784,
        "sold": 0,
        "reserved": 0,
        "available": 784,
        "housefull": 0,
        "fastfilling": 0
      },
      {
        "venue": "ini-simara",
        "total_shows": 3,
        "seats": 597,
        "sold": 0,
        "reserved": 0,
        "available": 597,
        "housefull": 0,
        "fastfilling": 0
      },
      {
        "venue": "ini-cinemas-devchuli",
        "total_shows": 2,
        "seats": 584,
        "sold": 0,
        "reserved": 0,
        "available": 584,
        "housefull": 0,
        "fastfilling": 0
      }
    ]
  },
  {
    "movie_id": "aqDu6NBWYyN8KWnPNt3Jh3",
    "movie_name": "Mortal Kombat 2",
    "total_shows": 4,
    "seats": 503,
    "sold": 0,
    "reserved": 15,
    "available": 488,
    "housefull": 0,
    "fastfilling": 0,
    "venues": [
      {
        "venue": "fcube",
        "total_shows": 1,
        "seats": 198,
        "sold": 0,
        "reserved": 15,
        "available": 183,
        "housefull": 0,
        "fastfilling": 0
      },
      {
        "venue": "qfx-durbar",
        "total_shows": 1,
        "seats": 53,
        "sold": 0,
        "reserved": 0,
        "available": 53,
        "housefull": 0,
        "fastfilling": 0
      },
      {
        "venue": "ranjana-cineplex",
        "total_shows": 1,
        "seats": 118,
        "sold": 0,
        "reserved": 0,
        "available": 118,
        "housefull": 0,
        "fastfilling": 0
      },
      {
        "venue": "qfx-cineflix-itahari",
        "total_shows": 1,
        "seats": 134,
        "sold": 0,
        "reserved": 0,
        "available": 134,
        "housefull": 0,
        "fastfilling": 0
      }
    ]
  },
  {
    "movie_id": "EV4uzZ3KYu6GMDAVK3uycY",
    "movie_name": "Paralko Aago",
    "total_shows": 8,
    "seats": 1510,
    "sold": 3,
    "reserved": 44,
    "available": 1463,
    "housefull": 0,
    "fastfilling": 0,
    "venues": [
      {
        "venue": "fcube",
        "total_shows": 2,
        "seats": 424,
        "sold": 3,
        "reserved": 29,
        "available": 392,
        "housefull": 0,
        "fastfilling": 0
      },
      {
        "venue": "qfx-bhaktapur",
        "total_shows": 2,
        "seats": 414,
        "sold": 0,
        "reserved": 15,
        "available": 399,
        "housefull": 0,
        "fastfilling": 0
      },
      {
        "venue": "ranjana-cineplex",
        "total_shows": 1,
        "seats": 118,
        "sold": 0,
        "reserved": 0,
        "available": 118,
        "housefull": 0,
        "fastfilling": 0
      },
      {
        "venue": "ini-qbox-butwal",
        "total_shows": 1,
        "seats": 196,
        "sold": 0,
        "reserved": 0,
        "available": 196,
        "housefull": 0,
        "fastfilling": 0
      },
      {
        "venue": "ini-lotse-ktm",
        "total_shows": 1,
        "seats": 240,
        "sold": 0,
        "reserved": 0,
        "available": 240,
        "housefull": 0,
        "fastfilling": 0
      },
      {
        "venue": "ini-simara",
        "total_shows": 1,
        "seats": 118,
        "sold": 0,
        "reserved": 0,
        "available": 118,
        "housefull": 0,
        "fastfilling": 0
      }
    ]
  },
  {
    "movie_id": "U4zoKohWHiitMu75sAxbFF",
    "movie_name": "Malati Mangale",
    "total_shows": 18,
    "seats": 3330,
    "sold": 2,
    "reserved": 44,
    "available": 3284,
    "housefull": 0,
    "fastfilling": 0,
    "venues": [
      {
        "venue": "fcube",
        "total_shows": 2,
        "seats": 408,
        "sold": 2,
        "reserved": 25,
        "available": 381,
        "housefull": 0,
        "fastfilling": 0
      },
      {
        "venue": "qfx-bhaktapur",
        "total_shows": 2,
        "seats": 455,
        "sold": 0,
        "reserved": 18,
        "available": 437,
        "housefull": 0,
        "fastfilling": 0
      },
      {
        "venue": "ranjana-cineplex",
        "total_shows": 1,
        "seats": 118,
        "sold": 0,
        "reserved": 0,
        "available": 118,
        "housefull": 0,
        "fastfilling": 0
      },
      {
        "venue": "birat-cine",
        "total_shows": 2,
        "seats": 244,
        "sold": 0,
        "reserved": 0,
        "available": 244,
        "housefull": 0,
        "fastfilling": 0
      },
      {
        "venue": "qfx-cineflix-itahari",
        "total_shows": 2,
        "seats": 268,
        "sold": 0,
        "reserved": 0,
        "available": 268,
        "housefull": 0,
        "fastfilling": 0
      },
      {
        "venue": "ini-cinemas-nb-center",
        "total_shows": 2,
        "seats": 354,
        "sold": 0,
        "reserved": 0,
        "available": 354,
        "housefull": 0,
        "fastfilling": 0
      },
      {
        "venue": "ini-lotse-ktm",
        "total_shows": 2,
        "seats": 480,
        "sold": 0,
        "reserved": 0,
        "available": 480,
        "housefull": 0,
        "fastfilling": 0
      },
      {
        "venue": "bishwojyoti-cineplex",
        "total_shows": 1,
        "seats": 201,
        "sold": 0,
        "reserved": 1,
        "available": 200,
        "housefull": 0,
        "fastfilling": 0
      },
      {
        "venue": "ini-qbox-butwal",
        "total_shows": 2,
        "seats": 392,
        "sold": 0,
        "reserved": 0,
        "available": 392,
        "housefull": 0,
        "fastfilling": 0
      },
      {
        "venue": "ini-cinemas-devchuli",
        "total_shows": 1,
        "seats": 292,
        "sold": 0,
        "reserved": 0,
        "available": 292,
        "housefull": 0,
        "fastfilling": 0
      },
      {
        "venue": "ini-simara",
        "total_shows": 1,
        "seats": 118,
        "sold": 0,
        "reserved": 0,
        "available": 118,
        "housefull": 0,
        "fastfilling": 0
      }
    ]
  },
  {
    "movie_id": "sXcRvU5SWKdVk9e9ZZJTCC",
    "movie_name": "Krishnavataram",
    "total_shows": 8,
    "seats": 1171,
    "sold": 2,
    "reserved": 15,
    "available": 1154,
    "housefull": 0,
    "fastfilling": 0,
    "venues": [
      {
        "venue": "fcube",
        "total_shows": 1,
        "seats": 198,
        "sold": 2,
        "reserved": 15,
        "available": 181,
        "housefull": 0,
        "fastfilling": 0
      },
      {
        "venue": "qfx-durbar",
        "total_shows": 1,
        "seats": 51,
        "sold": 0,
        "reserved": 0,
        "available": 51,
        "housefull": 0,
        "fastfilling": 0
      },
      {
        "venue": "qfx-bhaktapur",
        "total_shows": 1,
        "seats": 207,
        "sold": 0,
        "reserved": 0,
        "available": 207,
        "housefull": 0,
        "fastfilling": 0
      },
      {
        "venue": "birat-cine",
        "total_shows": 1,
        "seats": 122,
        "sold": 0,
        "reserved": 0,
        "available": 122,
        "housefull": 0,
        "fastfilling": 0
      },
      {
        "venue": "ranjana-cineplex",
        "total_shows": 1,
        "seats": 164,
        "sold": 0,
        "reserved": 0,
        "available": 164,
        "housefull": 0,
        "fastfilling": 0
      },
      {
        "venue": "qfx-cineflix-itahari",
        "total_shows": 1,
        "seats": 134,
        "sold": 0,
        "reserved": 0,
        "available": 134,
        "housefull": 0,
        "fastfilling": 0
      },
      {
        "venue": "ini-cinemas-nb-center",
        "total_shows": 1,
        "seats": 177,
        "sold": 0,
        "reserved": 0,
        "available": 177,
        "housefull": 0,
        "fastfilling": 0
      },
      {
        "venue": "ini-simara",
        "total_shows": 1,
        "seats": 118,
        "sold": 0,
        "reserved": 0,
        "available": 118,
        "housefull": 0,
        "fastfilling": 0
      }
    ]
  },
  {
    "movie_id": "FmEC2Rk4gFM6wiGaWgXUpm",
    "movie_name": "Michael",
    "total_shows": 6,
    "seats": 1003,
    "sold": 37,
    "reserved": 16,
    "available": 950,
    "housefull": 0,
    "fastfilling": 0,
    "venues": [
      {
        "venue": "fcube",
        "total_shows": 1,
        "seats": 210,
        "sold": 37,
        "reserved": 16,
        "available": 157,
        "housefull": 0,
        "fastfilling": 0
      },
      {
        "venue": "qfx-durbar",
        "total_shows": 1,
        "seats": 53,
        "sold": 0,
        "reserved": 0,
        "available": 53,
        "housefull": 0,
        "fastfilling": 0
      },
      {
        "venue": "ranjana-cineplex",
        "total_shows": 2,
        "seats": 282,
        "sold": 0,
        "reserved": 0,
        "available": 282,
        "housefull": 0,
        "fastfilling": 0
      },
      {
        "venue": "qfx-bhaktapur",
        "total_shows": 1,
        "seats": 248,
        "sold": 0,
        "reserved": 0,
        "available": 248,
        "housefull": 0,
        "fastfilling": 0
      },
      {
        "venue": "ini-cinemas-nb-center",
        "total_shows": 1,
        "seats": 210,
        "sold": 0,
        "reserved": 0,
        "available": 210,
        "housefull": 0,
        "fastfilling": 0
      }
    ]
  },
  {
    "movie_id": "xToQFjHfKS5uyo4F9uJmoL",
    "movie_name": "The Devil Wears Prada 2",
    "total_shows": 3,
    "seats": 155,
    "sold": 0,
    "reserved": 0,
    "available": 155,
    "housefull": 0,
    "fastfilling": 0,
    "venues": [
      {
        "venue": "qfx-durbar",
        "total_shows": 3,
        "seats": 155,
        "sold": 0,
        "reserved": 0,
        "available": 155,
        "housefull": 0,
        "fastfilling": 0
      }
    ]
  },
  {
    "movie_id": "UiB82iFPd63iHcjiGjhcXg",
    "movie_name": "Bhooth Bangla",
    "total_shows": 3,
    "seats": 593,
    "sold": 0,
    "reserved": 32,
    "available": 561,
    "housefull": 0,
    "fastfilling": 0,
    "venues": [
      {
        "venue": "fcube",
        "total_shows": 1,
        "seats": 212,
        "sold": 0,
        "reserved": 14,
        "available": 198,
        "housefull": 0,
        "fastfilling": 0
      },
      {
        "venue": "qfx-bhaktapur",
        "total_shows": 1,
        "seats": 247,
        "sold": 0,
        "reserved": 18,
        "available": 229,
        "housefull": 0,
        "fastfilling": 0
      },
      {
        "venue": "qfx-cineflix-itahari",
        "total_shows": 1,
        "seats": 134,
        "sold": 0,
        "reserved": 0,
        "available": 134,
        "housefull": 0,
        "fastfilling": 0
      }
    ]
  },
  {
    "movie_id": "SoFzLZp6Q3wZ35PshW3zj5",
    "movie_name": "Raja Shivaji",
    "total_shows": 1,
    "seats": 164,
    "sold": 0,
    "reserved": 0,
    "available": 164,
    "housefull": 0,
    "fastfilling": 0,
    "venues": [
      {
        "venue": "ranjana-cineplex",
        "total_shows": 1,
        "seats": 164,
        "sold": 0,
        "reserved": 0,
        "available": 164,
        "housefull": 0,
        "fastfilling": 0
      }
    ]
  }
]