[
  {
    "movie_id": "zDquhoHrfUHpyVzquamLCN",
    "movie_name": "Dhurandhar - The Revenge",
    "total_shows": 342,
    "seats": 67481,
    "sold": 22324,
    "reserved": 3616,
    "available": 41541,
    "housefull": 8,
    "fastfilling": 135,
    "venues": [
      {
        "venue": "big-movies",
        "total_shows": 12,
        "seats": 3592,
        "sold": 1581,
        "reserved": 539,
        "available": 1472,
        "housefull": 0,
        "fastfilling": 8
      },
      {
        "venue": "ini-lotse-ktm",
        "total_shows": 7,
        "seats": 1680,
        "sold": 273,
        "reserved": 117,
        "available": 1290,
        "housefull": 0,
        "fastfilling": 1
      },
      {
        "venue": "ini-cinemas-nb-center",
        "total_shows": 7,
        "seats": 1371,
        "sold": 559,
        "reserved": 125,
        "available": 687,
        "housefull": 0,
        "fastfilling": 4
      },
      {
        "venue": "fcube",
        "total_shows": 10,
        "seats": 2072,
        "sold": 963,
        "reserved": 214,
        "available": 895,
        "housefull": 0,
        "fastfilling": 7
      },
      {
        "venue": "ranjana-cineplex",
        "total_shows": 9,
        "seats": 1645,
        "sold": 444,
        "reserved": 216,
        "available": 985,
        "housefull": 0,
        "fastfilling": 3
      },
      {
        "venue": "kirtipur-cineplex",
        "total_shows": 6,
        "seats": 1158,
        "sold": 361,
        "reserved": 67,
        "available": 730,
        "housefull": 0,
        "fastfilling": 2
      },
      {
        "venue": "bishwojyoti-cineplex",
        "total_shows": 6,
        "seats": 870,
        "sold": 369,
        "reserved": 46,
        "available": 455,
        "housefull": 0,
        "fastfilling": 3
      },
      {
        "venue": "infinity-movies",
        "total_shows": 7,
        "seats": 1186,
        "sold": 169,
        "reserved": 14,
        "available": 1003,
        "housefull": 0,
        "fastfilling": 1
      },
      {
        "venue": "ini-qbox-butwal",
        "total_shows": 7,
        "seats": 1372,
        "sold": 618,
        "reserved": 105,
        "available": 649,
        "housefull": 0,
        "fastfilling": 4
      },
      {
        "venue": "mangyo-jana-jyoti-cinemas",
        "total_shows": 3,
        "seats": 927,
        "sold": 26,
        "reserved": 4,
        "available": 897,
        "housefull": 0,
        "fastfilling": 0
      },
      {
        "venue": "cineroyale",
        "total_shows": 11,
        "seats": 2114,
        "sold": 620,
        "reserved": 19,
        "available": 1475,
        "housefull": 0,
        "fastfilling": 2
      },
      {
        "venue": "city-cinema",
        "total_shows": 8,
        "seats": 1148,
        "sold": 533,
        "reserved": 55,
        "available": 560,
        "housefull": 0,
        "fastfilling": 6
      },
      {
        "venue": "central-multiplex",
        "total_shows": 8,
        "seats": 1840,
        "sold": 914,
        "reserved": 130,
        "available": 796,
        "housefull": 0,
        "fastfilling": 6
      },
      {
        "venue": "vfx-cinemas",
        "total_shows": 9,
        "seats": 1895,
        "sold": 274,
        "reserved": 101,
        "available": 1520,
        "housefull": 0,
        "fastfilling": 1
      },
      {
        "venue": "pathivara-cine-plaza",
        "total_shows": 6,
        "seats": 1374,
        "sold": 187,
        "reserved": 81,
        "available": 1106,
        "housefull": 0,
        "fastfilling": 1
      },
      {
        "venue": "Unknown",
        "total_shows": 2,
        "seats": 0,
        "sold": 0,
        "reserved": 0,
        "available": 0,
        "housefull": 0,
        "fastfilling": 0
      },
      {
        "venue": "ini-cinemas-devchuli",
        "total_shows": 3,
        "seats": 876,
        "sold": 8,
        "reserved": 0,
        "available": 868,
        "housefull": 0,
        "fastfilling": 0
      },
      {
        "venue": "qfx-durbar",
        "total_shows": 8,
        "seats": 416,
        "sold": 335,
        "reserved": 11,
        "available": 70,
        "housefull": 3,
        "fastfilling": 4
      },
      {
        "venue": "sts-cinema",
        "total_shows": 3,
        "seats": 1182,
        "sold": 222,
        "reserved": 161,
        "available": 799,
        "housefull": 0,
        "fastfilling": 0
      },
      {
        "venue": "one-cinemas-new-baneshwor",
        "total_shows": 11,
        "seats": 1845,
        "sold": 1185,
        "reserved": 6,
        "available": 654,
        "housefull": 1,
        "fastfilling": 7
      },
      {
        "venue": "one-cinemas-kalimati",
        "total_shows": 8,
        "seats": 1148,
        "sold": 505,
        "reserved": 4,
        "available": 639,
        "housefull": 0,
        "fastfilling": 2
      },
      {
        "venue": "dmax-cinemas",
        "total_shows": 6,
        "seats": 1002,
        "sold": 436,
        "reserved": 0,
        "available": 566,
        "housefull": 0,
        "fastfilling": 2
      },
      {
        "venue": "omax-cinema",
        "total_shows": 3,
        "seats": 1134,
        "sold": 154,
        "reserved": 37,
        "available": 943,
        "housefull": 0,
        "fastfilling": 0
      },
      {
        "venue": "oasis-cinema",
        "total_shows": 3,
        "seats": 475,
        "sold": 39,
        "reserved": 6,
        "available": 430,
        "housefull": 0,
        "fastfilling": 0
      },
      {
        "venue": "bsr-movies",
        "total_shows": 6,
        "seats": 1128,
        "sold": 130,
        "reserved": 202,
        "available": 796,
        "housefull": 0,
        "fastfilling": 1
      },
      {
        "venue": "suvakamna-cinemas",
        "total_shows": 3,
        "seats": 570,
        "sold": 42,
        "reserved": 8,
        "available": 520,
        "housefull": 0,
        "fastfilling": 0
      },
      {
        "venue": "birat-cine",
        "total_shows": 3,
        "seats": 507,
        "sold": 0,
        "reserved": 3,
        "available": 504,
        "housefull": 0,
        "fastfilling": 0
      },
      {
        "venue": "bamel-cinemas",
        "total_shows": 3,
        "seats": 411,
        "sold": 18,
        "reserved": 2,
        "available": 391,
        "housefull": 0,
        "fastfilling": 0
      },
      {
        "venue": "qfx-civil",
        "total_shows": 10,
        "seats": 3630,
        "sold": 1791,
        "reserved": 175,
        "available": 1664,
        "housefull": 0,
        "fastfilling": 6
      },
      {
        "venue": "qfx-chhaya",
        "total_shows": 9,
        "seats": 1154,
        "sold": 574,
        "reserved": 13,
        "available": 567,
        "housefull": 0,
        "fastfilling": 6
      },
      {
        "venue": "qfx-square-mall",
        "total_shows": 12,
        "seats": 1936,
        "sold": 701,
        "reserved": 19,
        "available": 1216,
        "housefull": 0,
        "fastfilling": 6
      },
      {
        "venue": "qs-cinemas",
        "total_shows": 9,
        "seats": 1426,
        "sold": 576,
        "reserved": 14,
        "available": 836,
        "housefull": 0,
        "fastfilling": 5
      },
      {
        "venue": "qfx-bhaktapur",
        "total_shows": 11,
        "seats": 2601,
        "sold": 1297,
        "reserved": 179,
        "available": 1125,
        "housefull": 0,
        "fastfilling": 8
      },
      {
        "venue": "pokhara-cineplex",
        "total_shows": 8,
        "seats": 2292,
        "sold": 410,
        "reserved": 90,
        "available": 1792,
        "housefull": 0,
        "fastfilling": 0
      },
      {
        "venue": "qfx-jalma",
        "total_shows": 8,
        "seats": 2132,
        "sold": 637,
        "reserved": 181,
        "available": 1314,
        "housefull": 0,
        "fastfilling": 2
      },
      {
        "venue": "chitwan-cineplex",
        "total_shows": 8,
        "seats": 1448,
        "sold": 516,
        "reserved": 81,
        "available": 851,
        "housefull": 0,
        "fastfilling": 4
      },
      {
        "venue": "qfx-skyline",
        "total_shows": 11,
        "seats": 1396,
        "sold": 1214,
        "reserved": 14,
        "available": 168,
        "housefull": 4,
        "fastfilling": 7
      },
      {
        "venue": "qfx-butwal",
        "total_shows": 7,
        "seats": 1292,
        "sold": 631,
        "reserved": 149,
        "available": 512,
        "housefull": 0,
        "fastfilling": 5
      },
      {
        "venue": "qfx-apex-mall",
        "total_shows": 3,
        "seats": 600,
        "sold": 27,
        "reserved": 6,
        "available": 567,
        "housefull": 0,
        "fastfilling": 0
      },
      {
        "venue": "qfx-bageshwori",
        "total_shows": 7,
        "seats": 2022,
        "sold": 58,
        "reserved": 8,
        "available": 1956,
        "housefull": 0,
        "fastfilling": 0
      },
      {
        "venue": "qfx-cineflix-itahari",
        "total_shows": 8,
        "seats": 1072,
        "sold": 247,
        "reserved": 8,
        "available": 817,
        "housefull": 0,
        "fastfilling": 1
      },
      {
        "venue": "midtown",
        "total_shows": 8,
        "seats": 1400,
        "sold": 569,
        "reserved": 63,
        "available": 768,
        "housefull": 0,
        "fastfilling": 5
      },
      {
        "venue": "friends-cinema-butwal-royal-cine-hub",
        "total_shows": 4,
        "seats": 852,
        "sold": 35,
        "reserved": 2,
        "available": 815,
        "housefull": 0,
        "fastfilling": 0
      },
      {
        "venue": "elite-cinemas",
        "total_shows": 6,
        "seats": 1071,
        "sold": 195,
        "reserved": 100,
        "available": 776,
        "housefull": 0,
        "fastfilling": 0
      },
      {
        "venue": "qfx-labim",
        "total_shows": 12,
        "seats": 2180,
        "sold": 1191,
        "reserved": 180,
        "available": 809,
        "housefull": 0,
        "fastfilling": 8
      },
      {
        "venue": "dm-cinemas",
        "total_shows": 4,
        "seats": 896,
        "sold": 1,
        "reserved": 1,
        "available": 894,
        "housefull": 0,
        "fastfilling": 0
      },
      {
        "venue": "kawaswoti-cinemax",
        "total_shows": 3,
        "seats": 774,
        "sold": 14,
        "reserved": 2,
        "available": 758,
        "housefull": 0,
        "fastfilling": 0
      },
      {
        "venue": "qfx-one-stop-mall",
        "total_shows": 8,
        "seats": 1084,
        "sold": 670,
        "reserved": 55,
        "available": 359,
        "housefull": 0,
        "fastfilling": 7
      },
      {
        "venue": "gsf-cinema",
        "total_shows": 2,
        "seats": 286,
        "sold": 0,
        "reserved": 2,
        "available": 284,
        "housefull": 0,
        "fastfilling": 0
      },
      {
        "venue": "kamal-binayak-cinemas",
        "total_shows": 3,
        "seats": 225,
        "sold": 0,
        "reserved": 0,
        "available": 225,
        "housefull": 0,
        "fastfilling": 0
      },
      {
        "venue": "sk-cinemas",
        "total_shows": 3,
        "seats": 774,
        "sold": 5,
        "reserved": 1,
        "available": 768,
        "housefull": 0,
        "fastfilling": 0
      }
    ]
  },
  {
    "movie_id": "aQWrEZXzxfbRCKcQhTNidH",
    "movie_name": "Project Hail Mary",
    "total_shows": 19,
    "seats": 3001,
    "sold": 180,
    "reserved": 55,
    "available": 2766,
    "housefull": 0,
    "fastfilling": 0,
    "venues": [
      {
        "venue": "ini-cinemas-nb-center",
        "total_shows": 1,
        "seats": 177,
        "sold": 11,
        "reserved": 7,
        "available": 159,
        "housefull": 0,
        "fastfilling": 0
      },
      {
        "venue": "bishwojyoti-cineplex",
        "total_shows": 1,
        "seats": 89,
        "sold": 1,
        "reserved": 0,
        "available": 88,
        "housefull": 0,
        "fastfilling": 0
      },
      {
        "venue": "fcube",
        "total_shows": 1,
        "seats": 198,
        "sold": 1,
        "reserved": 12,
        "available": 185,
        "housefull": 0,
        "fastfilling": 0
      },
      {
        "venue": "qfx-durbar",
        "total_shows": 1,
        "seats": 51,
        "sold": 5,
        "reserved": 0,
        "available": 46,
        "housefull": 0,
        "fastfilling": 0
      },
      {
        "venue": "qfx-butwal",
        "total_shows": 1,
        "seats": 196,
        "sold": 7,
        "reserved": 4,
        "available": 185,
        "housefull": 0,
        "fastfilling": 0
      },
      {
        "venue": "big-movies",
        "total_shows": 1,
        "seats": 279,
        "sold": 25,
        "reserved": 0,
        "available": 254,
        "housefull": 0,
        "fastfilling": 0
      },
      {
        "venue": "one-cinemas-new-baneshwor",
        "total_shows": 1,
        "seats": 67,
        "sold": 11,
        "reserved": 0,
        "available": 56,
        "housefull": 0,
        "fastfilling": 0
      },
      {
        "venue": "infinity-movies",
        "total_shows": 1,
        "seats": 154,
        "sold": 2,
        "reserved": 0,
        "available": 152,
        "housefull": 0,
        "fastfilling": 0
      },
      {
        "venue": "bsr-movies",
        "total_shows": 1,
        "seats": 180,
        "sold": 3,
        "reserved": 17,
        "available": 160,
        "housefull": 0,
        "fastfilling": 0
      },
      {
        "venue": "ranjana-cineplex",
        "total_shows": 1,
        "seats": 118,
        "sold": 11,
        "reserved": 8,
        "available": 99,
        "housefull": 0,
        "fastfilling": 0
      },
      {
        "venue": "qfx-chhaya",
        "total_shows": 2,
        "seats": 222,
        "sold": 18,
        "reserved": 0,
        "available": 204,
        "housefull": 0,
        "fastfilling": 0
      },
      {
        "venue": "qfx-cineflix-itahari",
        "total_shows": 1,
        "seats": 134,
        "sold": 4,
        "reserved": 0,
        "available": 130,
        "housefull": 0,
        "fastfilling": 0
      },
      {
        "venue": "qfx-civil",
        "total_shows": 1,
        "seats": 259,
        "sold": 35,
        "reserved": 5,
        "available": 219,
        "housefull": 0,
        "fastfilling": 0
      },
      {
        "venue": "chitwan-cineplex",
        "total_shows": 1,
        "seats": 219,
        "sold": 2,
        "reserved": 0,
        "available": 217,
        "housefull": 0,
        "fastfilling": 0
      },
      {
        "venue": "qfx-labim",
        "total_shows": 1,
        "seats": 183,
        "sold": 35,
        "reserved": 2,
        "available": 146,
        "housefull": 0,
        "fastfilling": 0
      },
      {
        "venue": "qs-cinemas",
        "total_shows": 1,
        "seats": 129,
        "sold": 4,
        "reserved": 0,
        "available": 125,
        "housefull": 0,
        "fastfilling": 0
      },
      {
        "venue": "qfx-square-mall",
        "total_shows": 1,
        "seats": 139,
        "sold": 5,
        "reserved": 0,
        "available": 134,
        "housefull": 0,
        "fastfilling": 0
      },
      {
        "venue": "qfx-bhaktapur",
        "total_shows": 1,
        "seats": 207,
        "sold": 0,
        "reserved": 0,
        "available": 207,
        "housefull": 0,
        "fastfilling": 0
      }
    ]
  },
  {
    "movie_id": "TrAcSfZv4oSLw47hzBudCQ",
    "movie_name": "Aa Bata Aama",
    "total_shows": 25,
    "seats": 4777,
    "sold": 7,
    "reserved": 43,
    "available": 4727,
    "housefull": 0,
    "fastfilling": 0,
    "venues": [
      {
        "venue": "bishwojyoti-cineplex",
        "total_shows": 1,
        "seats": 201,
        "sold": 0,
        "reserved": 0,
        "available": 201,
        "housefull": 0,
        "fastfilling": 0
      },
      {
        "venue": "mangyo-jana-jyoti-cinemas",
        "total_shows": 1,
        "seats": 309,
        "sold": 0,
        "reserved": 0,
        "available": 309,
        "housefull": 0,
        "fastfilling": 0
      },
      {
        "venue": "fcube",
        "total_shows": 1,
        "seats": 210,
        "sold": 3,
        "reserved": 14,
        "available": 193,
        "housefull": 0,
        "fastfilling": 0
      },
      {
        "venue": "ini-qbox-butwal",
        "total_shows": 1,
        "seats": 196,
        "sold": 0,
        "reserved": 0,
        "available": 196,
        "housefull": 0,
        "fastfilling": 0
      },
      {
        "venue": "kirtipur-cineplex",
        "total_shows": 1,
        "seats": 285,
        "sold": 0,
        "reserved": 0,
        "available": 285,
        "housefull": 0,
        "fastfilling": 0
      },
      {
        "venue": "cineroyale",
        "total_shows": 1,
        "seats": 126,
        "sold": 0,
        "reserved": 0,
        "available": 126,
        "housefull": 0,
        "fastfilling": 0
      },
      {
        "venue": "ini-lotse-ktm",
        "total_shows": 1,
        "seats": 240,
        "sold": 0,
        "reserved": 0,
        "available": 240,
        "housefull": 0,
        "fastfilling": 0
      },
      {
        "venue": "pathivara-cine-plaza",
        "total_shows": 2,
        "seats": 458,
        "sold": 0,
        "reserved": 0,
        "available": 458,
        "housefull": 0,
        "fastfilling": 0
      },
      {
        "venue": "dmax-cinemas",
        "total_shows": 2,
        "seats": 260,
        "sold": 0,
        "reserved": 0,
        "available": 260,
        "housefull": 0,
        "fastfilling": 0
      },
      {
        "venue": "sts-cinema",
        "total_shows": 1,
        "seats": 394,
        "sold": 0,
        "reserved": 9,
        "available": 385,
        "housefull": 0,
        "fastfilling": 0
      },
      {
        "venue": "bsr-movies",
        "total_shows": 1,
        "seats": 180,
        "sold": 0,
        "reserved": 15,
        "available": 165,
        "housefull": 0,
        "fastfilling": 0
      },
      {
        "venue": "oasis-cinema",
        "total_shows": 1,
        "seats": 133,
        "sold": 0,
        "reserved": 0,
        "available": 133,
        "housefull": 0,
        "fastfilling": 0
      },
      {
        "venue": "big-movies",
        "total_shows": 1,
        "seats": 270,
        "sold": 0,
        "reserved": 0,
        "available": 270,
        "housefull": 0,
        "fastfilling": 0
      },
      {
        "venue": "vfx-cinemas",
        "total_shows": 1,
        "seats": 247,
        "sold": 0,
        "reserved": 1,
        "available": 246,
        "housefull": 0,
        "fastfilling": 0
      },
      {
        "venue": "one-cinemas-new-baneshwor",
        "total_shows": 1,
        "seats": 67,
        "sold": 0,
        "reserved": 0,
        "available": 67,
        "housefull": 0,
        "fastfilling": 0
      },
      {
        "venue": "ranjana-cineplex",
        "total_shows": 1,
        "seats": 118,
        "sold": 0,
        "reserved": 0,
        "available": 118,
        "housefull": 0,
        "fastfilling": 0
      },
      {
        "venue": "suvakamna-cinemas",
        "total_shows": 1,
        "seats": 190,
        "sold": 0,
        "reserved": 0,
        "available": 190,
        "housefull": 0,
        "fastfilling": 0
      },
      {
        "venue": "qfx-apex-mall",
        "total_shows": 1,
        "seats": 120,
        "sold": 0,
        "reserved": 0,
        "available": 120,
        "housefull": 0,
        "fastfilling": 0
      },
      {
        "venue": "qfx-bageshwori",
        "total_shows": 1,
        "seats": 290,
        "sold": 4,
        "reserved": 4,
        "available": 282,
        "housefull": 0,
        "fastfilling": 0
      },
      {
        "venue": "himaz-cinema",
        "total_shows": 2,
        "seats": 150,
        "sold": 0,
        "reserved": 0,
        "available": 150,
        "housefull": 0,
        "fastfilling": 0
      },
      {
        "venue": "kamal-binayak-cinemas",
        "total_shows": 1,
        "seats": 75,
        "sold": 0,
        "reserved": 0,
        "available": 75,
        "housefull": 0,
        "fastfilling": 0
      },
      {
        "venue": "sk-cinemas",
        "total_shows": 1,
        "seats": 258,
        "sold": 0,
        "reserved": 0,
        "available": 258,
        "housefull": 0,
        "fastfilling": 0
      }
    ]
  },
  {
    "movie_id": "GqKfdqKoF8PsqNjiArS2yb",
    "movie_name": "Anjila",
    "total_shows": 1,
    "seats": 143,
    "sold": 0,
    "reserved": 4,
    "available": 139,
    "housefull": 0,
    "fastfilling": 0,
    "venues": [
      {
        "venue": "gsf-cinema",
        "total_shows": 1,
        "seats": 143,
        "sold": 0,
        "reserved": 4,
        "available": 139,
        "housefull": 0,
        "fastfilling": 0
      }
    ]
  },
  {
    "movie_id": "H2tbajrvASeefJpeWN3AAY",
    "movie_name": "Laalimaa",
    "total_shows": 1,
    "seats": 75,
    "sold": 0,
    "reserved": 0,
    "available": 75,
    "housefull": 0,
    "fastfilling": 0,
    "venues": [
      {
        "venue": "himaz-cinema",
        "total_shows": 1,
        "seats": 75,
        "sold": 0,
        "reserved": 0,
        "available": 75,
        "housefull": 0,
        "fastfilling": 0
      }
    ]
  }
]